active/__init__.py
active/core/__init__.py
active/core/loop.py
active/core/metrics/__init__.py
active/core/metrics/area.py
active/core/metrics/wss.py
active/core/strategies/__init__.py
active/core/strategies/alps.py
active/core/strategies/badge.py
active/core/strategies/egl.py
active/core/strategies/random.py
active/core/strategies/strategy.py
active/core/strategies/uncertainty.py
active/core/utils/__init__.py
active/core/utils/data.py
active/core/utils/gradnorm.py
active/core/utils/model.py
active/core/utils/sequence.py
active/helpers/__init__.py
active/helpers/engine.py
active/helpers/evaluator.py
active/helpers/metrics.py
active/helpers/params.py
active/helpers/processor.py
active/helpers/schedulers.py
active/helpers/trainer.py
active/rl/__init__.py
active/rl/callbacks.py
active/rl/extractors/__init__.py
active/rl/extractors/extractor.py
active/rl/extractors/transformer.py
active/rl/stream/__init__.py
active/rl/stream/env.py
active/rl/stream/model.py
active/scripts/__init__.py
active/scripts/run_active.py
active/scripts/run_rl_active.py
active/scripts/run_train.py
active_transformers-0.2.1.dist-info/LICENSE
active_transformers-0.2.1.dist-info/METADATA
active_transformers-0.2.1.dist-info/WHEEL
active_transformers-0.2.1.dist-info/entry_points.txt
active_transformers-0.2.1.dist-info/top_level.txt
active_transformers-0.2.1.dist-info/RECORD
